text2dataset/__init__.py
text2dataset/_version.py
text2dataset/main.py
text2dataset/reader.py
text2dataset/translator.py
text2dataset/utils.py
text2dataset/writer.py
text2dataset-0.2.4.dist-info/METADATA
text2dataset-0.2.4.dist-info/WHEEL
text2dataset-0.2.4.dist-info/entry_points.txt
text2dataset-0.2.4.dist-info/licenses/LICENSE
text2dataset-0.2.4.dist-info/RECORD
