Metadata-Version: 2.3
Name: text2dataset
Version: 0.2.4
Summary: Easily turn large English text datasets into Japanese text datasets using open LLMs
Project-URL: Repository, https://github.com/llm-jp/text2dataset
Author-email: speed1313 <speedtry13@icloud.com>
License: MIT License
Requires-Python: >=3.12.1
Requires-Dist: datasets>=3.0.0
Requires-Dist: deepl>=1.19.1
Requires-Dist: openai>=1.52.2
Requires-Dist: python-dotenv>=1.0.1
Requires-Dist: transformers==4.45.2
Requires-Dist: vllm>=0.6.1
Requires-Dist: wandb>=0.18.0
